Metadata-Version: 2.1
Name: blur-clip-board-image-cli
Version: 0.0.4
Summary: Blur clip board image command line tool for macOS
Home-page: https://github.com/kenchan0130/blur-clip-board-image-for-macOS
Author: Tadayuki Onishi
License: MIT
Platform: UNKNOWN
